arxplorer/__init__.py
arxplorer/agent/__init__.py
arxplorer/agent/arxiv_searcher.py
arxplorer/agent/assessor.py
arxplorer/agent/citation_retriever.py
arxplorer/agent/orchestrator.py
arxplorer/agent/query_agent.py
arxplorer/agent/references_extractor.py
arxplorer/agent/training/__init__.py
arxplorer/agent/training/arxiv_search_trainer.py
arxplorer/agent/training/mipro_v2_zeroshot_optimized_embeddings.json
arxplorer/agent/training/mipro_v2_zeroshot_optimized_size.json
arxplorer/agent/training/optimized_relevance_extractor.json
arxplorer/agent/training/references_extractor_trainer.py
arxplorer/agent/training/train_dataset.json
arxplorer/common/__init__.py
arxplorer/common/arxiv_api.py
arxplorer/common/common.py
arxplorer/common/limiter.py
arxplorer/common/semanticscholar.py
arxplorer/configuration.py
arxplorer/fix_dspy/__init__.py
arxplorer/fix_dspy/custom_adapter.py
arxplorer/persitence/__init__.py
arxplorer/persitence/database.py
arxplorer/server.py
arxplorer/ui/__init__.py
arxplorer/ui/assets/style.css
arxplorer/ui/dash_app.py
arxplorer/ui/pages/__init__.py
arxplorer/ui/pages/cards.py
arxplorer/ui/pages/papers.py
arxplorer/ui/pages/settings.py
arxplorer-0.1.1.dist-info/LICENSE
arxplorer-0.1.1.dist-info/METADATA
arxplorer-0.1.1.dist-info/WHEEL
arxplorer-0.1.1.dist-info/entry_points.txt
arxplorer-0.1.1.dist-info/RECORD
