Metadata-Version: 2.3
Name: arxplorer
Version: 0.1.1
Summary: An advanced system for searching, retrieving, and analyzing academic papers from arXiv using AI-powered agents.
License: Apache-2.0
Keywords: arxiv,research,academic,papers,AI,literature-review
Author: Marco Fago
Author-email: fago.marco.ai@gmail.com
Requires-Python: >=3.10,<3.13
Classifier: Development Status :: 3 - Alpha
Classifier: Intended Audience :: Developers
Classifier: Intended Audience :: Science/Research
Classifier: License :: OSI Approved :: Apache Software License
Classifier: Programming Language :: Python :: 3
Classifier: Programming Language :: Python :: 3.10
Classifier: Programming Language :: Python :: 3.11
Classifier: Programming Language :: Python :: 3.12
Classifier: Topic :: Scientific/Engineering
Classifier: Topic :: Scientific/Engineering :: Artificial Intelligence
Requires-Dist: arize-phoenix (>=7.5.1,<8.0.0)
Requires-Dist: arxiv (>=2.1.3,<3.0.0)
Requires-Dist: black (>=25.1.0,<26.0.0)
Requires-Dist: click (>=8.1.8,<9.0.0)
Requires-Dist: dash (>=2.18.2,<3.0.0)
Requires-Dist: dash-bootstrap-components (>=1.6.0,<2.0.0)
Requires-Dist: docling (>=2.15.1,<3.0.0)
Requires-Dist: dspy (==2.5.43)
Requires-Dist: openinference-instrumentation-dspy (>=0.1.14,<0.2.0)
Requires-Dist: opentelemetry-exporter-otlp (>=1.29.0,<2.0.0)
Requires-Dist: opentelemetry-sdk (>=1.29.0,<2.0.0)
Requires-Dist: pydantic (>=2.10.4,<3.0.0)
Requires-Dist: pymupdf4llm (>=0.0.17,<0.0.18)
Requires-Dist: python-dotenv (>=1.0.1,<2.0.0)
Requires-Dist: sqlalchemy (>=2.0.38,<3.0.0)
Requires-Dist: transformers (>=4.48.2,<5.0.0)
Requires-Dist: waitress (>=3.0.2,<4.0.0)
Project-URL: Bug Tracker, https://github.com/marfago/ArXplorer/issues
Project-URL: Documentation, https://github.com/marfago/ArXplorer#readme
Project-URL: Homepage, https://github.com/marfago/ArXplorer
Project-URL: Repository, https://github.com/marfago/ArXplorer
